DARSEP/DARSEP_PMLM.py
DARSEP/DARSEP_SPRLM.py
DARSEP/__init__.py
DARSEP/mcts_alphaZero_mutate_expand_m_p_gfp.py
DARSEP/p_v_net_3.py
DARSEP/sequence_env_m_p.py
DARSEP/test_api.py
DARSEP-1.1.dist-info/METADATA
DARSEP-1.1.dist-info/WHEEL
DARSEP-1.1.dist-info/top_level.txt
DARSEP-1.1.dist-info/RECORD
